pprof/__init__.py
pprof/cpu.py
pprof-0.2.0.dist-info/LICENSE
pprof-0.2.0.dist-info/WHEEL
pprof-0.2.0.dist-info/METADATA
pprof-0.2.0.dist-info/RECORD
