Metadata-Version: 2.1
Name: pprof
Version: 0.2.0
Summary: Python profiling tool
License: MIT
Keywords: timing,timer,profiling,profiler,perfomance
Author: mirecl
Author-email: grazhdankov@gmail.com
Requires-Python: >=3.6.2,<4.0
Classifier: License :: OSI Approved :: MIT License
Classifier: Operating System :: OS Independent
Classifier: Programming Language :: Python
Classifier: Programming Language :: Python :: 3
Classifier: Programming Language :: Python :: 3.10
Classifier: Programming Language :: Python :: 3.6
Classifier: Programming Language :: Python :: 3.7
Classifier: Programming Language :: Python :: 3.8
Classifier: Programming Language :: Python :: 3.9
Classifier: Topic :: Software Development
Requires-Dist: line-profiler (>=3.5.1,<4.0.0)
Project-URL: Documentation, https://github.com/mirecl/pprof
Project-URL: Homepage, https://github.com/mirecl/pprof
Project-URL: Repository, https://github.com/mirecl/pprof
